artifacts/__init__.py
artifacts/vSAN/Alert_Definitions.xml
artifacts/vSAN/Dashboards.zip
artifacts/vSAN/Supermetrics.json
artifacts/vSAN/Views.zip
artifacts/vSAN/__init__.py
examples/__init__.py
examples/run_send-data-to-vrops.bat
main/__init__.py
main/encrypt-passwords.py
main/env.json
main/notifications-template.json
main/notifications.py
main/send-data-to-vrops.py
main/encrypted_files/__init__.py
main/utils/FolderUtility.py
main/utils/LogUtility.py
main/utils/PSUtility.py
main/utils/SosRest.py
main/utils/__init__.py
vmware_cloud_foundation_health_monitoring-2.2.0.1003.dist-info/LICENSE
vmware_cloud_foundation_health_monitoring-2.2.0.1003.dist-info/METADATA
vmware_cloud_foundation_health_monitoring-2.2.0.1003.dist-info/NOTICE
vmware_cloud_foundation_health_monitoring-2.2.0.1003.dist-info/WHEEL
vmware_cloud_foundation_health_monitoring-2.2.0.1003.dist-info/top_level.txt
vmware_cloud_foundation_health_monitoring-2.2.0.1003.dist-info/RECORD
