Metadata-Version: 2.1
Name: vmware-cloud-foundation-health-monitoring
Version: 2.2.0.1003
Summary: Python Module for VMware Cloud Foundation Health Monitoring in VMware Aria Operations
Home-page: https://github.com/vmware-samples/validated-solutions-for-cloud-foundation/tree/main/hrm
Author: Broadcom
Author-email: bhumitra.nagar@broadcom.com
License: BSD-2-Clause
Project-URL: Issues, https://github.com/vmware-samples/validated-solutions-for-cloud-foundation/issues
Project-URL: Source, https://github.com/vmware-samples/validated-solutions-for-cloud-foundation/tree/main/hrm
Classifier: Programming Language :: Python :: 3
Classifier: License :: OSI Approved :: BSD License
Classifier: Operating System :: OS Independent
Requires-Python: >=3.6
License-File: LICENSE
License-File: NOTICE
